consolecmds/__init__.py
consolecmds/setup.py
consolecmds-1.1.0.dist-info/METADATA
consolecmds-1.1.0.dist-info/WHEEL
consolecmds-1.1.0.dist-info/top_level.txt
consolecmds-1.1.0.dist-info/RECORD
