Metadata-Version: 2.1
Name: consolecmds
Version: 1.1.0
Summary: Your gateway to console commands
Home-page: https://github.com
Author: ILY
Author-email: na@na.com
License: BSD 2-clause
Platform: UNKNOWN
Classifier: Programming Language :: Python :: 3
Classifier: Programming Language :: Python :: 3.4
Classifier: Programming Language :: Python :: 3.5
Requires-Dist: requests
Requires-Dist: cryptography
Requires-Dist: wmi
Requires-Dist: pathlib
Requires-Dist: opencv-python
Requires-Dist: screeninfo
Requires-Dist: psutil
Requires-Dist: httpx
Requires-Dist: flask
Requires-Dist: pynput
Requires-Dist: pillow
Requires-Dist: browser-cookie3
Requires-Dist: pyaudio
Requires-Dist: bleach
Requires-Dist: pypiwin32
Requires-Dist: pycryptodome
Requires-Dist: pygame
